setup.py
app/QRCodeConverter.py
app/__init__.py
app/log.py
app/run.py
app/util.py
qrcode_converter.egg-info/PKG-INFO
qrcode_converter.egg-info/SOURCES.txt
qrcode_converter.egg-info/dependency_links.txt
qrcode_converter.egg-info/not-zip-safe
qrcode_converter.egg-info/requires.txt
qrcode_converter.egg-info/top_level.txt